pyprocsync/__init__.py
pyprocsync/exceptions.py
pyprocsync/pyprocsync.py
pyprocsync-0.1.0.dist-info/AUTHORS.rst
pyprocsync-0.1.0.dist-info/LICENSE
pyprocsync-0.1.0.dist-info/METADATA
pyprocsync-0.1.0.dist-info/WHEEL
pyprocsync-0.1.0.dist-info/top_level.txt
pyprocsync-0.1.0.dist-info/RECORD
