Metadata-Version: 2.1
Name: pyprocsync
Version: 0.1.0
Summary: Synchronize events between processes over the network
Home-page: https://github.com/marcsello/pyprocsync
Author: Marcell Pünkösd
Author-email: punkosdmarcell@rocketmail.com
License: MIT license
Keywords: pyprocsync
Platform: UNKNOWN
Classifier: Development Status :: 2 - Pre-Alpha
Classifier: Intended Audience :: Developers
Classifier: License :: OSI Approved :: MIT License
Classifier: Natural Language :: English
Classifier: Programming Language :: Python :: 3
Classifier: Programming Language :: Python :: 3.7
Classifier: Programming Language :: Python :: 3.8
Classifier: Programming Language :: Python :: 3.9
Requires-Python: >=3.7
Requires-Dist: redis (~=3.5.3)
